miangin/__init__.py
miangin/miangin.py
abzaramar-0.1.0.dist-info/METADATA
abzaramar-0.1.0.dist-info/WHEEL
abzaramar-0.1.0.dist-info/top_level.txt
abzaramar-0.1.0.dist-info/RECORD
