Metadata-Version: 2.4
Name: AbzarAmar
Version: 0.1.0
Summary: Simple statistics functions
Author: NEGAR MANSOURI
Requires-Python: >=3.6
Dynamic: author
Dynamic: description
Dynamic: description-content-type
Dynamic: requires-python
Dynamic: summary
